LICENSE
MANIFEST.in
README.rst
requirements.txt
setup.py
test_requirements.txt
kaiso/__init__.py
kaiso/exceptions.py
kaiso/iter_helpers.py
kaiso/migration_helpers.py
kaiso/persistence.py
kaiso/queries.py
kaiso/references.py
kaiso/relationships.py
kaiso/serialize.py
kaiso/test_helpers.py
kaiso/types.py
kaiso/utils.py
kaiso.egg-info/PKG-INFO
kaiso.egg-info/SOURCES.txt
kaiso.egg-info/dependency_links.txt
kaiso.egg-info/requires.txt
kaiso.egg-info/top_level.txt
kaiso.egg-info/zip-safe
kaiso/attributes/__init__.py
kaiso/attributes/bases.py
test/test_attributes.py
test/test_descriptors.py
test/test_dynamic_types.py
test/test_exceptions.py
test/test_labels.py
test/test_metaclasses.py
test/test_migration_helpers.py
test/test_queries.py
test/test_relationships.py
test/test_reparent.py
test/test_serialize.py
test/test_test_helpers.py
test/test_type_coercion.py
test/test_type_registry.py
test/test_types.py
test/test_unique.py
test/test_utils.py