Metadata-Version: 1.0
Name: kaiso
Version: 0.40.0
Summary: A queryable object persistence and relationship framework based on the Neo4j graph database.
Home-page: http://github.com/onefinestay/kaiso
Author: onefinestay
Author-email: engineering@onefinestay.com
License: Apache License, Version 2.0
Platform: UNKNOWN
Classifier: Programming Language :: Python
Classifier: Operating System :: MacOS :: MacOS X
Classifier: Operating System :: POSIX
Classifier: Programming Language :: Python :: 2.7
Classifier: Topic :: Internet
Classifier: Topic :: Software Development :: Libraries :: Python Modules
Classifier: Intended Audience :: Developers
